combilog.py
combilog-2.0.1.dist-info/LICENSE
combilog-2.0.1.dist-info/METADATA
combilog-2.0.1.dist-info/WHEEL
combilog-2.0.1.dist-info/top_level.txt
combilog-2.0.1.dist-info/RECORD
