Metadata-Version: 2.1
Name: combilog
Version: 2.0.1
Summary: A tool to interact with the combilog by Theodor Friedrichs.
Home-page: https://github.com/theendlessriver13/combilog
Author: Jonas Kittner
Author-email: theendlessriver13@users.noreply.github.com
License: MIT
Platform: UNKNOWN
Classifier: License :: OSI Approved :: MIT License
Classifier: Programming Language :: Python :: 3
Classifier: Programming Language :: Python :: 3 :: Only
Classifier: Programming Language :: Python :: 3.6
Classifier: Programming Language :: Python :: 3.7
Classifier: Programming Language :: Python :: 3.8
Classifier: Programming Language :: Python :: 3.9
Classifier: Programming Language :: Python :: Implementation :: CPython
Requires-Python: >=3.6.1
Requires-Dist: pyserial (>=3.4)
